testrail_megamigrator/__init__.py
testrail_megamigrator/forms.py
testrail_megamigrator/models.py
testrail_megamigrator/serializers.py
testrail_megamigrator/tasks.py
testrail_megamigrator/urls.py
testrail_megamigrator/views.py
testrail_megamigrator/migrations/0001_initial.py
testrail_megamigrator/migrations/0002_rename_dumpfile_path_testrailsettings_testy_attachments_url.py
testrail_megamigrator/migrations/0003_auto_20230324_0928.py
testrail_megamigrator/migrations/0004_auto_20230411_1856.py
testrail_megamigrator/migrations/0005_testrailsettings_custom_fields_matcher.py
testrail_megamigrator/migrations/__init__.py
testrail_megamigrator/migrator_lib/__init__.py
testrail_megamigrator/migrator_lib/config.py
testrail_megamigrator/migrator_lib/migrator_service.py
testrail_megamigrator/migrator_lib/testrail.py
testrail_megamigrator/migrator_lib/testy.py
testrail_megamigrator/migrator_lib/utils.py
testrail_megamigrator/static/testrail_migrator/css/bootstrap.min.css
testrail_megamigrator/static/testrail_migrator/js/bootstrap.min.js
testrail_megamigrator/static/testrail_migrator/js/prettify_json.js
testrail_megamigrator/templates/migrator_backups_list.html
testrail_megamigrator/templates/migrator_base.html
testrail_megamigrator/templates/migrator_configs_list.html
testrail_megamigrator/templates/migrator_confirm_delete.html
testrail_megamigrator/templates/migrator_download.html
testrail_megamigrator/templates/migrator_form.html
testrail_megamigrator/templates/migrator_settings_form.html
testrail_megamigrator/templates/task_status.html
testrail_megamigrator-0.0.2.dist-info/METADATA
testrail_megamigrator-0.0.2.dist-info/WHEEL
testrail_megamigrator-0.0.2.dist-info/entry_points.txt
testrail_megamigrator-0.0.2.dist-info/top_level.txt
testrail_megamigrator-0.0.2.dist-info/RECORD
